README.md
pyproject.toml
setup.py
rxpipes/__init__.py
rxpipes/concurrency.py
rxpipes/pipeline.py
rxpipes/utils.py
rxpipes/version.py
rxpipes.egg-info/PKG-INFO
rxpipes.egg-info/SOURCES.txt
rxpipes.egg-info/dependency_links.txt
rxpipes.egg-info/not-zip-safe
rxpipes.egg-info/requires.txt
rxpipes.egg-info/top_level.txt