Metadata-Version: 2.1
Name: rxpipes
Version: 0.0.4
Summary: UNKNOWN
Home-page: https://github.com/shirecoding/RxPipes
Author: shirecoding
Author-email: shirecoding@gmail.com
License: UNKNOWN
Download-URL: https://github.com/shirecoding/ModelMaker/archive/0.0.4.tar.gz
Platform: UNKNOWN
Classifier: Programming Language :: Python :: 3
Classifier: License :: OSI Approved :: MIT License
Classifier: Operating System :: OS Independent
Provides-Extra: test
Provides-Extra: docs
